Vector/__init__.py
Vector/vector.py
kitvector-0.0.2.dist-info/METADATA
kitvector-0.0.2.dist-info/WHEEL
kitvector-0.0.2.dist-info/top_level.txt
kitvector-0.0.2.dist-info/RECORD
